sklearn_relief.py
sklearn_relief-1.0.0a3.dist-info/DESCRIPTION.rst
sklearn_relief-1.0.0a3.dist-info/METADATA
sklearn_relief-1.0.0a3.dist-info/RECORD
sklearn_relief-1.0.0a3.dist-info/WHEEL
sklearn_relief-1.0.0a3.dist-info/metadata.json
sklearn_relief-1.0.0a3.dist-info/top_level.txt
