Metadata-Version: 2.0
Name: sklearn-relief
Version: 1.0.0a3
Summary: Implementation of the Relief family of algorithms for feature ranking
Home-page: https://gitlab.com/qafir/sklearn-relief
Author: Alfredo Mungo
Author-email: alfredo.mungo@protonmail.ch
License: UNKNOWN
Platform: UNKNOWN
Classifier: Development Status :: 3 - Alpha
Classifier: Intended Audience :: Science/Research
Classifier: License :: OSI Approved :: BSD License
Classifier: Operating System :: OS Independent
Classifier: Programming Language :: Python
Classifier: Topic :: Scientific/Engineering :: Information Analysis
Requires: numpy (>=1.13.3)
Requires: sklearn (>=0.19.1)
Requires-Python: >=3.0
